amISelected/__init__.py
amISelected/read_html.py
amISelected-0.1.1.dist-info/LICENSE
amISelected-0.1.1.dist-info/METADATA
amISelected-0.1.1.dist-info/WHEEL
amISelected-0.1.1.dist-info/entry_points.txt
amISelected-0.1.1.dist-info/top_level.txt
amISelected-0.1.1.dist-info/RECORD
