Metadata-Version: 2.1
Name: amISelected
Version: 0.1.1
Summary: A small repo to check whether you have been selected
Home-page: https://github.com/leoguignard/amISelected
Author: Leo Guignard
Author-email: leo.guignard@gmail.com
License: MIT
Project-URL: Bug Tracker, https://github.com/leoguignard/AmISelected/issues
Project-URL: Documentation, https://github.com/leoguignard/AmISelected#README.md
Project-URL: Source Code, https://github.com/leoguignard/AmISelected
Project-URL: User Support, https://github.com/leoguignard/AmISelected/issues
Classifier: Development Status :: 2 - Pre-Alpha
Classifier: Intended Audience :: Developers
Classifier: License :: OSI Approved :: MIT License
Classifier: Operating System :: OS Independent
Classifier: Programming Language :: Python
Classifier: Programming Language :: Python :: 3
Classifier: Programming Language :: Python :: 3 :: Only
Classifier: Programming Language :: Python :: 3.10
Classifier: Programming Language :: Python :: 3.11
Classifier: Programming Language :: Python :: 3.12
Requires-Python: >=3.10
License-File: LICENSE
